stream/__init__.py
stream/release.py
stream/stream.py
stream/varint.py
pystream_protobuf-1.6.4.dist-info/LICENSE
pystream_protobuf-1.6.4.dist-info/METADATA
pystream_protobuf-1.6.4.dist-info/WHEEL
pystream_protobuf-1.6.4.dist-info/entry_points.txt
pystream_protobuf-1.6.4.dist-info/top_level.txt
pystream_protobuf-1.6.4.dist-info/RECORD
