Metadata-Version: 2.1
Name: pystream-protobuf
Version: 1.6.4
Summary: Python implementation of stream library
Home-page: https://github.com/cartoonist/pystream-protobuf
Download-URL: https://github.com/cartoonist/pystream-protobuf/tarball/1.6.4
Author: Ali Ghaffaari
Author-email: ali.ghaffaari@mpi-inf.mpg.de
License: MIT
Keywords: stream protocol buffer protobuf
Classifier: Development Status :: 5 - Production/Stable
Classifier: License :: OSI Approved :: MIT License
Classifier: Programming Language :: Python :: 3
Classifier: Programming Language :: Python :: 3.5
Classifier: Programming Language :: Python :: 3.6
Classifier: Programming Language :: Python :: 3.7
Classifier: Programming Language :: Python :: 3.8
Classifier: Intended Audience :: Developers
License-File: LICENSE
Requires-Dist: protobuf (>=3.4.0)
Requires-Dist: async-generator (>=1.10)
Requires-Dist: click (>=6.0.0)
Requires-Dist: future
Provides-Extra: test
Requires-Dist: nose (>=1.0) ; extra == 'test'
Requires-Dist: coverage ; extra == 'test'
